jupyter_datainputtable/__init__.py
jupyter_datainputtable/_version.py
jupyter_datainputtable-0.8.1.data/data/share/jupyter/labextensions/jupyter-datainputtable/package.json
jupyter_datainputtable-0.8.1.data/data/share/jupyter/labextensions/jupyter-datainputtable/static/509.59cd2f368a46a1cc05a5.js
jupyter_datainputtable-0.8.1.data/data/share/jupyter/labextensions/jupyter-datainputtable/static/728.2a1e0f6b96ae830b5435.js
jupyter_datainputtable-0.8.1.data/data/share/jupyter/labextensions/jupyter-datainputtable/static/remoteEntry.2ad4edde82fc7303ce47.js
jupyter_datainputtable-0.8.1.data/data/share/jupyter/labextensions/jupyter-datainputtable/static/style.js
jupyter_datainputtable-0.8.1.data/data/share/jupyter/labextensions/jupyter-datainputtable/static/third-party-licenses.json
jupyter_datainputtable-0.8.1.data/data/share/jupyter/labextensions/jupyter-datainputtable/install.json
jupyter_datainputtable-0.8.1.dist-info/METADATA
jupyter_datainputtable-0.8.1.dist-info/WHEEL
jupyter_datainputtable-0.8.1.dist-info/licenses/LICENSE
jupyter_datainputtable-0.8.1.dist-info/RECORD
