Metadata-Version: 2.4
Name: jupyter_datainputtable
Version: 0.8.1
Dynamic: Keywords
Summary: Predefined data input tables for Jupyter notebooks
Project-URL: Homepage, https://github.com/JupyterPhysSciLab/jupyter-datainputtable
Project-URL: Bug Tracker, https://github.com/JupyterPhysSciLab/jupyter-datainputtable/issues
Project-URL: Repository, https://github.com/JupyterPhysSciLab/jupyter-datainputtable.git
Author-email: Jonathan Gutow <gutow@uwosh.edu>
License: BSD 3-Clause License
License-File: LICENSE
Classifier: Framework :: Jupyter
Classifier: Framework :: Jupyter :: JupyterLab
Classifier: Framework :: Jupyter :: JupyterLab :: 4
Classifier: Framework :: Jupyter :: JupyterLab :: Extensions
Classifier: Framework :: Jupyter :: JupyterLab :: Extensions :: Prebuilt
Classifier: License :: OSI Approved :: BSD License
Classifier: Programming Language :: Python
Classifier: Programming Language :: Python :: 3
Classifier: Programming Language :: Python :: 3.8
Classifier: Programming Language :: Python :: 3.9
Classifier: Programming Language :: Python :: 3.10
Classifier: Programming Language :: Python :: 3.11
Classifier: Programming Language :: Python :: 3.12
Requires-Python: >=3.8
Requires-Dist: jpslutils>=0.7.0
Requires-Dist: notebook>=7.0.0
Requires-Dist: numpy>=2.0.0
Requires-Dist: pandas>=2.0.0
